malaysian_news_parser/__init__.py
malaysian_news_parser/base_parser.py
malaysian_news_parser/base_scraper.py
malaysian_news_parser/config/__init__.py
malaysian_news_parser/config/publisher_config.py
malaysian_news_parser/parsers/__init__.py
malaysian_news_parser/parsers/dynamic_parser.py
malaysian_news_parser/parsers/rss_parser.py
malaysian_news_parser/parsers/static_parser.py
malaysian_news_parser/scraper/__init__.py
malaysian_news_parser/scraper/requests_scraper.py
malaysian_news_parser/scraper/rss_scraper.py
malaysian_news_parser/scraper/scraper.py
malaysian_news_parser/scraper/selenium_scraper.py
malaysian_news_parser/tests/__init__.py
malaysian_news_parser/tests/test_base_parser.py
malaysian_news_parser/tests/test_dynamic_parser.py
malaysian_news_parser/tests/test_publisher_configs.py
malaysian_news_parser/tests/test_static_parser.py
malaysian_news_parser-0.1.4.dist-info/licenses/LICENSE
malaysian_news_parser-0.1.4.dist-info/METADATA
malaysian_news_parser-0.1.4.dist-info/WHEEL
malaysian_news_parser-0.1.4.dist-info/top_level.txt
malaysian_news_parser-0.1.4.dist-info/RECORD
