Metadata-Version: 2.4
Name: malaysian_news_parser
Version: 0.1.4
Summary: A python library for parsing news articles
Home-page: https://github.com/squimptech/Malaysian_News_Parser
Author: Squimptech
Author-email: enquiry@squimptech.com
Classifier: Programming Language :: Python :: 3
Classifier: License :: OSI Approved :: MIT License
Classifier: Operating System :: OS Independent
Requires-Python: >=3.6
License-File: LICENSE
Requires-Dist: requests
Requires-Dist: beautifulsoup4
Requires-Dist: selenium
Dynamic: author
Dynamic: author-email
Dynamic: classifier
Dynamic: description
Dynamic: description-content-type
Dynamic: home-page
Dynamic: license-file
Dynamic: requires-dist
Dynamic: requires-python
Dynamic: summary
